{
  "query": {
    "pages": {
      "157128": {
        "pageid": 157128,
        "ns": 0,
        "title": "Charles de Gaulle Airport",
        "extract": "Paris Charles de Gaulle Airport (French: Aéroport de Paris-Charles-de-Gaulle), also known as Roissy Airport, is the largest international airport in France and one of the busiest airports in Europe. Opened in 1974, it is located in Roissy-en-France, 23 km northeast of Paris. It is named after Charles de Gaulle (1890–1970), leader of the Free French Forces during the Second World War, founder of the French Fifth Republic and President of France from 1959 to 1969.",
        "thumbnail": {
          "source": "https://upload.wikimedia.org/wikipedia/commons/thumb/6/6b/Paris_-_Charles_de_Gaulle_International_Airport_Terminal_2F_-_2401.jpg/500px-Paris_-_Charles_de_Gaulle_International_Airport_Terminal_2F_-_2401.jpg",
          "width": 500,
          "height": 333
        }
      }
    }
  }
}